django_admin_tui/__about__.py
django_admin_tui/__init__.py
django_admin_tui/tui.py
django_admin_tui/management/__init__.py
django_admin_tui/management/commands/__init__.py
django_admin_tui/management/commands/admin_tui.py
django_admin_tui-0.0.1.dist-info/METADATA
django_admin_tui-0.0.1.dist-info/WHEEL
django_admin_tui-0.0.1.dist-info/licenses/LICENSE.txt
django_admin_tui-0.0.1.dist-info/RECORD
