Metadata-Version: 2.3
Name: django-admin-tui
Version: 0.0.1
Summary: Django Admin in the terminal.
Project-URL: Documentation, https://github.com/valberg/django-admin-tui#readme
Project-URL: Issues, https://github.com/valberg/django-admin-tui/issues
Project-URL: Source, https://github.com/valberg/django-admin-tui
Author-email: Víðir Valberg Guðmundsson <valberg@orn.li>
License-Expression: MIT
License-File: LICENSE.txt
Classifier: Development Status :: 3 - Alpha
Classifier: Programming Language :: Python
Classifier: Programming Language :: Python :: 3.9
Classifier: Programming Language :: Python :: 3.10
Classifier: Programming Language :: Python :: 3.11
Classifier: Programming Language :: Python :: 3.12
Requires-Python: >=3.9
Requires-Dist: django>=4.2
Requires-Dist: textual>=0.79
